{"nodes": [{"id": "d_toananhthanh_apps_web_src_components_videoplayer_tsx", "label": "VideoPlayer.tsx", "file_type": "code", "source_file": "D:\\ToanAnhThanh\\apps\\web\\src\\components\\VideoPlayer.tsx", "source_location": "L1"}, {"id": "components_videoplayer_videoplayer", "label": "VideoPlayer()", "file_type": "code", "source_file": "D:\\ToanAnhThanh\\apps\\web\\src\\components\\VideoPlayer.tsx", "source_location": "L12"}], "edges": [{"source": "d_toananhthanh_apps_web_src_components_videoplayer_tsx", "target": "react", "relation": "imports_from", "context": "import", "confidence": "EXTRACTED", "source_file": "D:\\ToanAnhThanh\\apps\\web\\src\\components\\VideoPlayer.tsx", "source_location": "L1", "weight": 1.0}, {"source": "d_toananhthanh_apps_web_src_components_videoplayer_tsx", "target": "d_toananhthanh_apps_web_src_lib_api_ts", "relation": "imports_from", "context": "import", "confidence": "EXTRACTED", "source_file": "D:\\ToanAnhThanh\\apps\\web\\src\\components\\VideoPlayer.tsx", "source_location": "L2", "weight": 1.0}, {"source": "d_toananhthanh_apps_web_src_components_videoplayer_tsx", "target": "lib_api_api", "relation": "imports", "context": "import", "confidence": "EXTRACTED", "source_file": "D:\\ToanAnhThanh\\apps\\web\\src\\components\\VideoPlayer.tsx", "source_location": "L2", "weight": 1.0}, {"source": "d_toananhthanh_apps_web_src_components_videoplayer_tsx", "target": "lib_api_reportactivity", "relation": "imports", "context": "import", "confidence": "EXTRACTED", "source_file": "D:\\ToanAnhThanh\\apps\\web\\src\\components\\VideoPlayer.tsx", "source_location": "L2", "weight": 1.0}, {"source": "d_toananhthanh_apps_web_src_components_videoplayer_tsx", "target": "d_toananhthanh_apps_web_src_lib_store_ts", "relation": "imports_from", "context": "import", "confidence": "EXTRACTED", "source_file": "D:\\ToanAnhThanh\\apps\\web\\src\\components\\VideoPlayer.tsx", "source_location": "L3", "weight": 1.0}, {"source": "d_toananhthanh_apps_web_src_components_videoplayer_tsx", "target": "lib_store_useauth", "relation": "imports", "context": "import", "confidence": "EXTRACTED", "source_file": "D:\\ToanAnhThanh\\apps\\web\\src\\components\\VideoPlayer.tsx", "source_location": "L3", "weight": 1.0}, {"source": "d_toananhthanh_apps_web_src_components_videoplayer_tsx", "target": "components_videoplayer_videoplayer", "relation": "contains", "confidence": "EXTRACTED", "source_file": "D:\\ToanAnhThanh\\apps\\web\\src\\components\\VideoPlayer.tsx", "source_location": "L12", "weight": 1.0}], "raw_calls": [{"caller_nid": "components_videoplayer_videoplayer", "callee": "useRef", "is_member_call": false, "source_file": "D:\\ToanAnhThanh\\apps\\web\\src\\components\\VideoPlayer.tsx", "source_location": "L13"}, {"caller_nid": "components_videoplayer_videoplayer", "callee": "useAuth", "is_member_call": false, "source_file": "D:\\ToanAnhThanh\\apps\\web\\src\\components\\VideoPlayer.tsx", "source_location": "L14"}, {"caller_nid": "components_videoplayer_videoplayer", "callee": "useState", "is_member_call": false, "source_file": "D:\\ToanAnhThanh\\apps\\web\\src\\components\\VideoPlayer.tsx", "source_location": "L15"}, {"caller_nid": "components_videoplayer_videoplayer", "callee": "useState", "is_member_call": false, "source_file": "D:\\ToanAnhThanh\\apps\\web\\src\\components\\VideoPlayer.tsx", "source_location": "L16"}, {"caller_nid": "components_videoplayer_videoplayer", "callee": "useState", "is_member_call": false, "source_file": "D:\\ToanAnhThanh\\apps\\web\\src\\components\\VideoPlayer.tsx", "source_location": "L17"}, {"caller_nid": "components_videoplayer_videoplayer", "callee": "useEffect", "is_member_call": false, "source_file": "D:\\ToanAnhThanh\\apps\\web\\src\\components\\VideoPlayer.tsx", "source_location": "L19"}, {"caller_nid": "components_videoplayer_videoplayer", "callee": "useEffect", "is_member_call": false, "source_file": "D:\\ToanAnhThanh\\apps\\web\\src\\components\\VideoPlayer.tsx", "source_location": "L28"}, {"caller_nid": "components_videoplayer_videoplayer", "callee": "useEffect", "is_member_call": false, "source_file": "D:\\ToanAnhThanh\\apps\\web\\src\\components\\VideoPlayer.tsx", "source_location": "L37"}, {"caller_nid": "components_videoplayer_videoplayer", "callee": "toLocaleTimeString", "is_member_call": true, "source_file": "D:\\ToanAnhThanh\\apps\\web\\src\\components\\VideoPlayer.tsx", "source_location": "L73"}]}